odoo8_addon_connector_salesforce-8.0.1.0.0-py2.7-nspkg.pth
odoo_addons/connector_salesforce/__openerp__.py
odoo_addons/connector_salesforce/backend.py
odoo_addons/connector_salesforce/__init__.py
odoo_addons/connector_salesforce/README.rst
odoo_addons/connector_salesforce/consumer.py
odoo_addons/connector_salesforce/salesforce_price_book_entry/backend.py
odoo_addons/connector_salesforce/salesforce_price_book_entry/importer.py
odoo_addons/connector_salesforce/salesforce_price_book_entry/__init__.py
odoo_addons/connector_salesforce/salesforce_price_book_entry/common.py
odoo_addons/connector_salesforce/salesforce_price_book_entry/view/backend_view.xml
odoo_addons/connector_salesforce/security/ir.model.access.csv
odoo_addons/connector_salesforce/salesforce_contact/backend.py
odoo_addons/connector_salesforce/salesforce_contact/importer.py
odoo_addons/connector_salesforce/salesforce_contact/__init__.py
odoo_addons/connector_salesforce/salesforce_contact/common.py
odoo_addons/connector_salesforce/salesforce_contact/view/res_partner_view.xml
odoo_addons/connector_salesforce/salesforce_contact/view/backend_view.xml
odoo_addons/connector_salesforce/lib/date_convertion.py
odoo_addons/connector_salesforce/lib/__init__.py
odoo_addons/connector_salesforce/lib/oauth2_utils.py
odoo_addons/connector_salesforce/salesforce_backend/backend_model.py
odoo_addons/connector_salesforce/salesforce_backend/__init__.py
odoo_addons/connector_salesforce/salesforce_backend/view/backend_model_view.xml
odoo_addons/connector_salesforce/salesforce_opportunity/backend.py
odoo_addons/connector_salesforce/salesforce_opportunity/importer.py
odoo_addons/connector_salesforce/salesforce_opportunity/__init__.py
odoo_addons/connector_salesforce/salesforce_opportunity/common.py
odoo_addons/connector_salesforce/salesforce_opportunity/view/backend_view.xml
odoo_addons/connector_salesforce/salesforce_account/backend.py
odoo_addons/connector_salesforce/salesforce_account/importer.py
odoo8_addon_connector_salesforce-8.0.1.0.0.dist-info/top_level.txt
odoo8_addon_connector_salesforce-8.0.1.0.0.dist-info/WHEEL
odoo8_addon_connector_salesforce-8.0.1.0.0.dist-info/RECORD
odoo8_addon_connector_salesforce-8.0.1.0.0.dist-info/metadata.json
odoo8_addon_connector_salesforce-8.0.1.0.0.dist-info/DESCRIPTION.rst
odoo8_addon_connector_salesforce-8.0.1.0.0.dist-info/METADATA
odoo8_addon_connector_salesforce-8.0.1.0.0.dist-info/namespace_packages.txt
