Metadata-Version: 2.0
Name: odoo8-addon-connector-salesforce
Version: 8.0.1.0.0
Summary: Provides core synchronization interfaces with Salesforce.
Home-page: UNKNOWN
Author: Camptocamp,Odoo Community Association (OCA)
Author-email: support@odoo-community.org
License: AGPL-3
Platform: UNKNOWN
Requires-Dist: odoo (<9.0a,>=8.0a)
Requires-Dist: odoo8-addon-connector
Requires-Dist: requests
Requires-Dist: simple-salesforce
Classifier: Programming Language :: Python :: 2.7
Classifier: Framework :: Odoo
Classifier: License :: OSI Approved :: GNU Affero General Public License v3
